metakb/__init__.py
metakb/cli.py
metakb/database.py
metakb/delta.py
metakb/exceptions.py
metakb/main.py
metakb/normalizers.py
metakb/query.py
metakb/schemas.py
metakb/version.py
metakb/harvesters/__init__.py
metakb/harvesters/base.py
metakb/harvesters/civic.py
metakb/harvesters/moa.py
metakb/transform/__init__.py
metakb/transform/base.py
metakb/transform/civic.py
metakb/transform/moa.py
metakb-1.1.0.dist-info/LICENSE
metakb-1.1.0.dist-info/METADATA
metakb-1.1.0.dist-info/WHEEL
metakb-1.1.0.dist-info/top_level.txt
metakb-1.1.0.dist-info/RECORD
