Metadata-Version: 2.1
Name: metakb
Version: 1.1.0
Summary: A search interface for cancer variant interpretations assembled by aggregating and harmonizing across multiple cancer variant interpretation knowledgebases.
Home-page: https://github.com/cancervariants/metakb
Author: VICC
Author-email: help@cancervariants.org
License: MIT
Platform: UNKNOWN
Classifier: Development Status :: 3 - Alpha
Classifier: Intended Audience :: Science/Research
Classifier: Intended Audience :: Developers
Classifier: Topic :: Scientific/Engineering :: Bio-Informatics
Classifier: License :: OSI Approved :: MIT License
Classifier: Programming Language :: Python :: 3
Classifier: Programming Language :: Python :: 3.8
Requires-Python: >=3.8
Requires-Dist: asyncclick
Requires-Dist: boto3
Requires-Dist: botocore
Requires-Dist: civicpy (>=2.0.0)
Requires-Dist: disease-normalizer[dev] (==0.2.15)
Requires-Dist: fastapi
Requires-Dist: ga4gh.vrs (==0.8.0dev0)
Requires-Dist: ga4gh.vrsatile.pydantic (==0.0.11)
Requires-Dist: gene-normalizer[dev] (==0.1.30)
Requires-Dist: jsondiff
Requires-Dist: neo4j
Requires-Dist: pydantic
Requires-Dist: requests
Requires-Dist: requests-cache
Requires-Dist: thera-py[dev] (==0.3.7)
Requires-Dist: uvicorn
Requires-Dist: variation-normalizer (==0.5.1)
